selenium_utilities/__init__.py
selenium_utilities/selenium_utilities.py
selenium_utilities-1.2.0.dist-info/LICENSE
selenium_utilities-1.2.0.dist-info/METADATA
selenium_utilities-1.2.0.dist-info/WHEEL
selenium_utilities-1.2.0.dist-info/top_level.txt
selenium_utilities-1.2.0.dist-info/RECORD
