Metadata-Version: 2.1
Name: selenium-utilities
Version: 1.2.0
Summary: Useful utilities for comfortable using selenium.
Home-page: https://github.com/DedInc/selenium_utilities
Author: Maehdakvan
Author-email: visitanimation@google.com
License: UNKNOWN
Project-URL: Bug Tracker, https://github.com/DedInc/selenium_utilities/issues
Platform: UNKNOWN
Classifier: Programming Language :: Python :: 3
Classifier: License :: OSI Approved :: MIT License
Classifier: Operating System :: OS Independent
Requires-Python: >=3.6
License-File: LICENSE
Requires-Dist: requests
Requires-Dist: lxml
